langchain_bytez_main/BytezChatModel.py
langchain_bytez_main/BytezLLM.py
langchain_bytez_main/BytezModelMixin.py
langchain_bytez_main/BytezStdOutCallbackHandler.py
langchain_bytez_main/__init__.py
langchain_bytez_main-0.0.1.dist-info/METADATA
langchain_bytez_main-0.0.1.dist-info/WHEEL
langchain_bytez_main-0.0.1.dist-info/top_level.txt
langchain_bytez_main-0.0.1.dist-info/RECORD
