Metadata-Version: 2.4
Name: langchain-bytez-main
Version: 0.0.1
Summary: Bytez langchain integration with advanced AI capabilities
Home-page: https://github.com/Bytez-com/langchain_bytez
Author: AIMLStudent
Project-URL: Bug Reports, https://github.com/Bytez-com/langchain_bytez/issues
Project-URL: Source, https://github.com/Bytez-com/langchain_bytez
Project-URL: Documentation, https://github.com/Bytez-com/langchain_bytez/blob/main/README.md
Keywords: langchain,bytez,llm,ai,chatbot,artificial-intelligence
Classifier: Development Status :: 4 - Beta
Classifier: Intended Audience :: Developers
Classifier: Topic :: Scientific/Engineering :: Artificial Intelligence
Classifier: Topic :: Software Development :: Libraries :: Python Modules
Classifier: Programming Language :: Python :: 3
Classifier: Programming Language :: Python :: 3.8
Classifier: Programming Language :: Python :: 3.9
Classifier: Programming Language :: Python :: 3.10
Classifier: Programming Language :: Python :: 3.11
Classifier: Programming Language :: Python :: 3.12
Classifier: License :: OSI Approved :: MIT License
Classifier: Operating System :: OS Independent
Requires-Python: >=3.8
Requires-Dist: langchain==0.3.17
Requires-Dist: requests>=2.25.0
Requires-Dist: pydantic>=1.10.0
Dynamic: author
Dynamic: classifier
Dynamic: description
Dynamic: description-content-type
Dynamic: home-page
Dynamic: keywords
Dynamic: project-url
Dynamic: requires-dist
Dynamic: requires-python
Dynamic: summary
